readable_code/__init__.py
readable_code/main.py
readable_code-1.2.dist-info/METADATA
readable_code-1.2.dist-info/WHEEL
readable_code-1.2.dist-info/top_level.txt
readable_code-1.2.dist-info/RECORD
