Metadata-Version: 2.4
Name: readable_code
Version: 1.2
Summary: Making totally readable code
Dynamic: description
Dynamic: description-content-type
Dynamic: summary
